reddstagram/__init__.py
reddstagram/auto.py
reddstagram-0.0.1.dist-info/LICENSE
reddstagram-0.0.1.dist-info/METADATA
reddstagram-0.0.1.dist-info/WHEEL
reddstagram-0.0.1.dist-info/top_level.txt
reddstagram-0.0.1.dist-info/RECORD
