Metadata-Version: 2.1
Name: reddstagram
Version: 0.0.1
Summary: Automated Reddit to Instagram
Home-page: UNKNOWN
Author: FOGT Solutions
Author-email: <contact@fogt-solutions.com>
License: UNKNOWN
Keywords: python,reddit,instagram
Platform: UNKNOWN
Requires-Dist: pillow
Requires-Dist: pathlib
Requires-Dist: instabot
Requires-Dist: praw
Requires-Dist: wget
